{
    "version": 2,
    "options": {
	"name": "Quizlet",
	"targetUrl": "https://quizlet.com/",
	"overwrite": true,
	"out": "temp",
	"icon": "resources/IconManager/output/Internet/Quizlet-Icon[Square].png"
    },
    "linux": {
	"options":{
	    
	},
	".desktop": {
	    "Name": "Quizlet",
	    "Comment": "Study things!",
	    "Icon": "quizlet"
	},
	"icon": "resources/IconManager/output/Internet/Quizlet-Icon[Square].png"
    },
    "win32": {
	"options":{
	    "icon": "resources/IconManager/output/Internet/Quizlet-Icon.ico"
	},
	"name": "Quizlet"
    }
}
